sadic/__init__.py
sadic/api.py
sadic/cli_config.py
sadic/cli_sadic.py
sadic/algorithm/__init__.py
sadic/algorithm/depth.py
sadic/algorithm/radius.py
sadic/pdb/__init__.py
sadic/pdb/pdbentity.py
sadic/pdb/result.py
sadic/quantizer/__init__.py
sadic/quantizer/quantizer.py
sadic/solid/__init__.py
sadic/solid/multisphere.py
sadic/solid/solid.py
sadic/solid/sphere.py
sadic/solid/voxel_solid.py
sadic/utils/__init__.py
sadic/utils/config.py
sadic/utils/repr.py
sadic-2.0.0.dist-info/LICENSE
sadic-2.0.0.dist-info/METADATA
sadic-2.0.0.dist-info/WHEEL
sadic-2.0.0.dist-info/entry_points.txt
sadic-2.0.0.dist-info/top_level.txt
sadic-2.0.0.dist-info/RECORD
